docs/docs/source/_static/logo315x318.png
speakerpy/__main__.py
speakerpy/lib_helper.py
speakerpy/lib_sl_text.py
speakerpy/lib_speak.py
speakerpy-0.1.2.dist-info/METADATA
speakerpy-0.1.2.dist-info/WHEEL
speakerpy-0.1.2.dist-info/RECORD
