Metadata-Version: 2.1
Name: speakerpy
Version: 0.1.2
Summary: `SpeakerPy` - это Python-библиотека для синтеза речи, основанная на моделях Silero Text-to-Speech.
Home-page: https://github.com/denisxab/speakerpy
Keywords: синтез речи,text-to-speech,озвучивание текста,python,Silero,TTS,аудио,голос,синтезатор голоса,чтение текста,оффлайн TTS,мультиязычный TTS,преобразование текста в речь,генерация речи,аудиокниги
Author: Denis Kustov
Author-email: pro-progerkustov@yandex.ru
Requires-Python: >=3.10,<4.0
Classifier: Programming Language :: Python :: 3
Classifier: Programming Language :: Python :: 3.10
Classifier: Programming Language :: Python :: 3.11
Requires-Dist: nltk (>=3.8.1,<4.0.0)
Requires-Dist: num2words (>=0.5.12,<0.6.0)
Requires-Dist: numpy (>=1.24.2,<2.0.0)
Requires-Dist: pydub (>=0.25.1,<0.26.0)
Requires-Dist: silero (>=0.4.1,<0.5.0)
Requires-Dist: sounddevice (>=0.4.6,<0.5.0)
Requires-Dist: soundfile (>=0.12.1,<0.13.0)
Requires-Dist: tqdm (>=4.65.0,<5.0.0)
Requires-Dist: transliterate (>=1.10.2,<2.0.0)
Project-URL: Repository, https://github.com/denisxab/speakerpy
